flatten_everything/LICENSE
flatten_everything/README.MD
flatten_everything/__init__.py
flatten_everything/requirements.txt
flatten_everything/thirdparty.json
flatten_everything-0.41.dist-info/LICENSE.rst
flatten_everything-0.41.dist-info/METADATA
flatten_everything-0.41.dist-info/WHEEL
flatten_everything-0.41.dist-info/top_level.txt
flatten_everything-0.41.dist-info/RECORD
