Metadata-Version: 2.1
Name: flatten-everything
Version: 0.41
Summary: Flattens everything - lists, tuples, dicts, np, pd... Option to protect iterables from being flattened
Home-page: https://github.com/hansalemaos/flatten_everything
Author: Johannes Fischer
Author-email: <aulasparticularesdealemaosp@gmail.com>
License: MIT
Keywords: flatten,pandas,dict,list,numpy,tuple,Tagsiter,nested,iterable,listsoflists,flattenjson,iter,explode,squeeze
Classifier: Development Status :: 4 - Beta
Classifier: Programming Language :: Python :: 3 :: Only
Classifier: Programming Language :: Python :: 3.9
Classifier: Topic :: Scientific/Engineering :: Visualization
Classifier: Topic :: Software Development :: Libraries :: Python Modules
Classifier: Topic :: Text Editors :: Text Processing
Classifier: Topic :: Text Processing :: General
Classifier: Topic :: Text Processing :: Indexing
Classifier: Topic :: Text Processing :: Filters
Classifier: Topic :: Utilities
License-File: LICENSE.rst
